nussl/__init__.py
nussl/core/__init__.py
nussl/core/audio_signal.py
nussl/core/constants.py
nussl/core/effects.py
nussl/core/efz_utils.py
nussl/core/migration.py
nussl/core/mixing.py
nussl/core/play_utils.py
nussl/core/utils.py
nussl/core/masks/__init__.py
nussl/core/masks/binary_mask.py
nussl/core/masks/mask_base.py
nussl/core/masks/soft_mask.py
nussl/core/templates/__init__.py
nussl/core/templates/multitrack.html
nussl/datasets/__init__.py
nussl/datasets/base_dataset.py
nussl/datasets/hooks.py
nussl/datasets/transforms.py
nussl/evaluation/__init__.py
nussl/evaluation/bss_eval.py
nussl/evaluation/evaluation_base.py
nussl/evaluation/precision_recall_fscore.py
nussl/evaluation/report_card.py
nussl/ml/__init__.py
nussl/ml/cluster.py
nussl/ml/confidence.py
nussl/ml/networks/__init__.py
nussl/ml/networks/builders.py
nussl/ml/networks/separation_model.py
nussl/ml/networks/modules/__init__.py
nussl/ml/networks/modules/blocks.py
nussl/ml/networks/modules/filter_bank.py
nussl/ml/train/__init__.py
nussl/ml/train/closures.py
nussl/ml/train/loss.py
nussl/ml/train/trainer.py
nussl/ml/unfold/__init__.py
nussl/ml/unfold/gaussian_mixture.py
nussl/separation/__init__.py
nussl/separation/base/__init__.py
nussl/separation/base/clustering_separation_base.py
nussl/separation/base/deep_mixin.py
nussl/separation/base/mask_separation_base.py
nussl/separation/base/nmf_mixin.py
nussl/separation/base/separation_base.py
nussl/separation/benchmark/__init__.py
nussl/separation/benchmark/high_low_pass_filter.py
nussl/separation/benchmark/ideal_binary_mask.py
nussl/separation/benchmark/ideal_ratio_mask.py
nussl/separation/benchmark/mix_as_estimate.py
nussl/separation/benchmark/wiener_filter.py
nussl/separation/composite/__init__.py
nussl/separation/composite/ensemble_clustering.py
nussl/separation/composite/overlap_add.py
nussl/separation/deep/__init__.py
nussl/separation/deep/deep_audio_estimation.py
nussl/separation/deep/deep_clustering.py
nussl/separation/deep/deep_mask_estimation.py
nussl-1.1.9.dist-info/LICENSE.md
nussl-1.1.9.dist-info/METADATA
nussl-1.1.9.dist-info/WHEEL
nussl-1.1.9.dist-info/top_level.txt
nussl-1.1.9.dist-info/RECORD
